{"data":[{"long_id":"6401","short_id":"01","name":"KABUPATEN PASER","lat":"-1.7175266","lon":"115.9467997","tz":"8"},{"long_id":"6402","short_id":"02","name":"KABUPATEN KUTAI BARAT","lat":"-0.4051796","lon":"115.8521764","tz":"8"},{"long_id":"6403","short_id":"03","name":"KABUPATEN KUTAI KARTANEGARA","lat":"-0.1336655","lon":"116.6081653","tz":"8"},{"long_id":"6404","short_id":"04","name":"KABUPATEN KUTAI TIMUR","lat":"0.9433774","lon":"116.9852422","tz":"8"},{"long_id":"6405","short_id":"05","name":"KABUPATEN BERAU","lat":"2.0450883","lon":"117.3616476","tz":"8"},{"long_id":"6409","short_id":"09","name":"KABUPATEN PENAJAM PASER UTARA","lat":"-1.2917094","lon":"116.5137964","tz":"8"},{"long_id":"6411","short_id":"11","name":"KABUPATEN MAHAKAM HULU","lat":"0.6998163","lon":"115.0228736","tz":"8"},{"long_id":"6471","short_id":"71","name":"KOTA BALIKPAPAN","lat":"-1.2379274","lon":"116.8528526","tz":"8"},{"long_id":"6472","short_id":"72","name":"KOTA SAMARINDA","lat":"-0.4948232","lon":"117.1436154","tz":"8"},{"long_id":"6474","short_id":"74","name":"KOTA BONTANG","lat":"0.120863","lon":"117.4800445","tz":"8"}]}